{"type":"FeatureCollection","crs":{"type":"name","properties":{"name":"EPSG:4326"}},"features":[{"type":"Feature","id":1,"geometry":{"type":"Point","coordinates":[77.411656195102239,23.160367042792391]},"properties":{"objectid":1,"sn":"Zone-18"}},{"type":"Feature","id":2,"geometry":{"type":"Point","coordinates":[77.500340806057835,23.143056183380189]},"properties":{"objectid":2,"sn":"zone-19"}},{"type":"Feature","id":3,"geometry":{"type":"Point","coordinates":[77.42865844999082,23.227421766708034]},"properties":{"objectid":3,"sn":"Zone-07"}},{"type":"Feature","id":4,"geometry":{"type":"Point","coordinates":[77.4286124424452,23.227452718635895]},"properties":{"objectid":4,"sn":"Zone-09"}},{"type":"Feature","id":5,"geometry":{"type":"Point","coordinates":[77.462094901551012,23.201007319303336]},"properties":{"objectid":5,"sn":"Zone-13"}},{"type":"Feature","id":6,"geometry":{"type":"Point","coordinates":[77.39375698068163,23.260086521249551]},"properties":{"objectid":6,"sn":"Zone-02"}},{"type":"Feature","id":7,"geometry":{"type":"Point","coordinates":[77.335556278609673,23.271352321796293]},"properties":{"objectid":7,"sn":"Zone-01"}},{"type":"Feature","id":8,"geometry":{"type":"Point","coordinates":[77.409577023570534,23.242157058700446]},"properties":{"objectid":8,"sn":"Zone-08"}},{"type":"Feature","id":9,"geometry":{"type":"Point","coordinates":[77.394304703968302,23.213636923396997]},"properties":{"objectid":9,"sn":"Zone-06"}},{"type":"Feature","id":10,"geometry":{"type":"Point","coordinates":[77.396205478075245,23.249948181357858]},"properties":{"objectid":10,"sn":"Zone-05"}},{"type":"Feature","id":11,"geometry":{"type":"Point","coordinates":[77.403182597458411,23.278445852298514]},"properties":{"objectid":11,"sn":"Zone-03"}},{"type":"Feature","id":12,"geometry":{"type":"Point","coordinates":[77.434667954042794,23.247891355645216]},"properties":{"objectid":12,"sn":"Zone-12"}},{"type":"Feature","id":13,"geometry":{"type":"Point","coordinates":[77.458302677760813,23.231417641685045]},"properties":{"objectid":13,"sn":"Zone-14"}},{"type":"Feature","id":14,"geometry":{"type":"Point","coordinates":[77.401097956273375,23.295328094141151]},"properties":{"objectid":14,"sn":"Zone-17"}},{"type":"Feature","id":15,"geometry":{"type":"Point","coordinates":[77.463536570804052,23.250641981285554]},"properties":{"objectid":15,"sn":"Zone-15"}},{"type":"Feature","id":16,"geometry":{"type":"Point","coordinates":[77.463509473704633,23.250682769714846]},"properties":{"objectid":16,"sn":"Zone-16"}},{"type":"Feature","id":17,"geometry":{"type":"Point","coordinates":[77.405179115411812,23.26137301671486]},"properties":{"objectid":17,"sn":"Zone-04"}},{"type":"Feature","id":18,"geometry":{"type":"Point","coordinates":[77.41962137287868,23.26680033667791]},"properties":{"objectid":18,"sn":"Zone-10"}},{"type":"Feature","id":19,"geometry":{"type":"Point","coordinates":[77.426695785313555,23.255065875391054]},"properties":{"objectid":19,"sn":"Zone-11"}}]}